string_randomizer/__init__.py
string_randomizer/randomizer.py
string_randomizer-0.1.0.dist-info/licenses/LICENSE
string_randomizer-0.1.0.dist-info/METADATA
string_randomizer-0.1.0.dist-info/WHEEL
string_randomizer-0.1.0.dist-info/top_level.txt
string_randomizer-0.1.0.dist-info/RECORD
